intruder_mcp/__init__.py
intruder_mcp/api_client.py
intruder_mcp/enums.py
intruder_mcp/server.py
mseep_intruder_mcp-0.1.1.dist-info/METADATA
mseep_intruder_mcp-0.1.1.dist-info/WHEEL
mseep_intruder_mcp-0.1.1.dist-info/entry_points.txt
mseep_intruder_mcp-0.1.1.dist-info/licenses/LICENSE.md
mseep_intruder_mcp-0.1.1.dist-info/RECORD
