Metadata-Version: 2.4
Name: mseep-intruder-mcp
Version: 0.1.1
Summary: MCP server for Intruder API
Author-email: mseep <support@skydeck.ai>
License-File: LICENSE.md
Requires-Dist: httpx>=0.24.0
Requires-Dist: mcp>=0.1.0
Requires-Dist: pydantic>=2.0.0
